MANIFEST.in
ebs.py
setup.cfg
setup.py
docs/.keep
ebs_gateway/__init__.py
ebs_gateway/admin.py
ebs_gateway/apps.py
ebs_gateway/forms.py
ebs_gateway/models.py
ebs_gateway/tests.py
ebs_gateway/urls.py
ebs_gateway/views.py
ebs_gateway/templates/gateway/callback.html
ebs_gateway/templates/gateway/index.html
ebs_gateway/templates/gateway/prepare_hash.html
ebs_payment.egg-info/PKG-INFO
ebs_payment.egg-info/SOURCES.txt
ebs_payment.egg-info/dependency_links.txt
ebs_payment.egg-info/not-zip-safe
ebs_payment.egg-info/top_level.txt