Metadata-Version: 1.1
Name: ebs-payment
Version: 0.8
Summary: This is a Django app for integrating with EBS payment SDK
Home-page: https://bitbucket.org/redpandas/ebs_gateway_python
Author: UNKNOWN
Author-email: souranil@theredpandas.com
License: MIT License
Platform: UNKNOWN
Classifier: Environment :: Web Environment
Classifier: Framework :: Django
Classifier: Framework :: Django :: 1.9
Classifier: Intended Audience :: Developers
Classifier: License :: OSI Approved :: MIT License
Classifier: Operating System :: OS Independent
Classifier: Programming Language :: Python
